LICENSE
MANIFEST.in
README.rst
_module.c
apr-1.7.0.tar.gz
apr-util-1.6.1.tar.gz
httpd-2.4.54.tar.gz
pcre-8.45.tar.gz
setup.py
mod_wsgi_httpd.egg-info/PKG-INFO
mod_wsgi_httpd.egg-info/SOURCES.txt
mod_wsgi_httpd.egg-info/dependency_links.txt
mod_wsgi_httpd.egg-info/entry_points.txt
mod_wsgi_httpd.egg-info/top_level.txt
src/__init__.py
src/apxs/__init__.py
src/apxs/__main__.py
src/httpd/__init__.py