Metadata-Version: 2.1
Name: mod-wsgi-httpd
Version: 2.4.54.1
Summary: Installer for Apache httpd server.
Home-page: http://www.modwsgi.org/
Author: Graham Dumpleton
Author-email: Graham.Dumpleton@gmail.com
Maintainer: Graham Dumpleton
Maintainer-email: Graham.Dumpleton@gmail.com
License: Apache License, Version 2.0
Platform: UNKNOWN
Classifier: Development Status :: 6 - Mature
Classifier: License :: OSI Approved :: Apache Software License
Classifier: Operating System :: MacOS :: MacOS X
Classifier: Operating System :: POSIX
Classifier: Operating System :: POSIX :: BSD
Classifier: Operating System :: POSIX :: Linux
Classifier: Operating System :: POSIX :: SunOS/Solaris
Classifier: Programming Language :: Python
Classifier: Programming Language :: Python :: Implementation :: CPython
Classifier: Programming Language :: Python :: 2.7
Classifier: Programming Language :: Python :: 3.5
Classifier: Programming Language :: Python :: 3.6
Classifier: Programming Language :: Python :: 3.7
Classifier: Programming Language :: Python :: 3.8
Classifier: Topic :: Internet :: WWW/HTTP :: WSGI
Classifier: Topic :: Internet :: WWW/HTTP :: WSGI :: Server
License-File: LICENSE
